ghidravol/__init__.py
ghidravol/commands_linux.py
ghidravol/commands_macos.py
ghidravol/commands_windows.py
ghidravol/gdb_commands.py
ghidravol/gdb_methods.py
ghidravol/gdb_vol.py
ghidravol/gdb_volpatch.py
ghidravol/lldb_commands.py
ghidravol/lldb_methods.py
ghidravol/lldb_vol.py
ghidravol/lldb_volpatch.py
ghidravol/tslist.py
ghidravol/volcmd.py
ghidravol-12.0.dist-info/licenses/LICENSE.txt
ghidravol-12.0.dist-info/METADATA
ghidravol-12.0.dist-info/WHEEL
ghidravol-12.0.dist-info/top_level.txt
ghidravol-12.0.dist-info/RECORD
