Metadata-Version: 2.4
Name: ghidravol
Version: 12.0
Summary: Ghidra's Plugin for Volatility
Author: Ghidra Development Team
Project-URL: Homepage, https://github.com/NationalSecurityAgency/ghidra
Project-URL: Bug Tracker, https://github.com/NationalSecurityAgency/ghidra/issues
Classifier: Programming Language :: Python :: 3
Classifier: License :: Other/Proprietary License
Classifier: Operating System :: OS Independent
Requires-Python: >=3.9
License-File: LICENSE.txt
Dynamic: license-file
